swarmrob/__init__.py
swarmrob/daemon.py
swarmrob/swarmrob.conf
swarmrob/swarmrob.py
swarmrob/worker.py
swarmrob/dockerengine/__init__.py
swarmrob/dockerengine/docker_container_list.py
swarmrob/dockerengine/docker_interface.py
swarmrob/logger/__init__.py
swarmrob/logger/evaluation_logger.py
swarmrob/logger/local_logger.py
swarmrob/logger/remote_logger.py
swarmrob/logger/remote_logging_server.py
swarmrob/swarmengine/__init__.py
swarmrob/swarmengine/mode.py
swarmrob/swarmengine/swarm.py
swarmrob/swarmengine/swarm_engine.py
swarmrob/swarmengine/swarm_engine_master.py
swarmrob/swarmengine/swarm_engine_worker.py
swarmrob/swarmengine/swarmrob_d.py
swarmrob/utils/__init__.py
swarmrob/utils/cmd_helper.py
swarmrob/utils/cmd_parser.py
swarmrob/utils/config.py
swarmrob/utils/errors.py
swarmrob/utils/network.py
swarmrob/utils/process_helper.py
swarmrob/utils/pyro_interface.py
swarmrob/utils/table_builder.py
Swarmrob_Worker-0.1.dist-info/METADATA
Swarmrob_Worker-0.1.dist-info/WHEEL
Swarmrob_Worker-0.1.dist-info/dependency_links.txt
Swarmrob_Worker-0.1.dist-info/entry_points.txt
Swarmrob_Worker-0.1.dist-info/top_level.txt
Swarmrob_Worker-0.1.dist-info/RECORD
